fasts2/__init__.py
fasts2/main.py
fasts2/task1.py
fasts2/task2.py
fasts2/utils.py
fasts2-0.0.4.dist-info/LICENSE
fasts2-0.0.4.dist-info/WHEEL
fasts2-0.0.4.dist-info/METADATA
fasts2-0.0.4.dist-info/RECORD
