Metadata-Version: 2.1
Name: fasts2
Version: 0.0.4
Summary: 🏎💨vroom vroom - S2 imagery downloader
Home-page: https://github.com/csaybar/fastS2
Author: Cesar Aybar
Author-email: fcesar.aybar@uv.es
Requires-Python: >=3.9,<4.0
Classifier: Programming Language :: Python :: 3
Classifier: Programming Language :: Python :: 3.9
Classifier: Programming Language :: Python :: 3.10
Requires-Dist: earthengine-api (>=0.1.400)
Requires-Dist: planetary-computer (>=1.0.0)
Requires-Dist: pydantic (>=2.0.0)
Requires-Dist: pystac-client (>=0.7.7)
Requires-Dist: shapely (>=2.0.4)
Requires-Dist: stackstac (>=0.5.0)
Requires-Dist: torch (>=2.0.0)
Project-URL: Documentation, https://csaybar.github.io/fastS2/
Project-URL: Repository, https://github.com/csaybar/fastS2
